sensibleapi/__init__.py
sensibleapi/sensibleapi.py
sensibleapi-0.0.17.dist-info/LICENSE
sensibleapi-0.0.17.dist-info/METADATA
sensibleapi-0.0.17.dist-info/WHEEL
sensibleapi-0.0.17.dist-info/top_level.txt
sensibleapi-0.0.17.dist-info/RECORD
