Metadata-Version: 2.1
Name: sensibleapi
Version: 0.0.17
Summary: Python SDK for Sensible, the developer-first platform for extracting structured data from documents so that you can build document-automation features into your SaaS products
Home-page: https://github.com/sensible-hq/sensible-api-py
Author: Sensible Technologies, Inc
Author-email: hello@sensible.so
License: MIT
License-File: LICENSE
Requires-Dist: requests
